<?xml version="1.0" encoding="UTF-8"?>
<root>
  <total_count>16</total_count>
  <artist id="16">
    <name><![CDATA[CARNÚN]]></name>
    <albums/>
    <albumcount>1</albumcount>
    <songs/>
    <songcount>9</songcount>
    <art><![CDATA[https://music.com.au/image.php?object_id=16&object_type=artist&auth=eeb9f1b6056246a7d563f479f518bb34]]></art>
    <flag>0</flag>
    <preciserating/>
    <rating/>
    <averagerating/>
    <mbid><![CDATA[]]></mbid>
    <summary><![CDATA[ ]]></summary>
    <time><![CDATA[4282]]></time>
    <yearformed>0</yearformed>
    <placeformed><![CDATA[]]></placeformed>
  </artist>
  <artist id="27">
    <name><![CDATA[Chi.Otic]]></name>
    <albums/>
    <albumcount>0</albumcount>
    <songs/>
    <songcount>1</songcount>
    <art><![CDATA[https://music.com.au/image.php?object_id=27&object_type=artist&auth=eeb9f1b6056246a7d563f479f518bb34]]></art>
    <flag>0</flag>
    <preciserating/>
    <rating/>
    <averagerating/>
    <mbid><![CDATA[7]]></mbid>
    <summary><![CDATA[ ]]></summary>
    <time><![CDATA[433]]></time>
    <yearformed>0</yearformed>
    <placeformed><![CDATA[]]></placeformed>
  </artist>
  <artist id="34">
    <name><![CDATA[Comedown Kid]]></name>
    <albums/>
    <albumcount>0</albumcount>
    <songs/>
    <songcount>1</songcount>
    <art><![CDATA[https://music.com.au/image.php?object_id=34&object_type=artist&auth=eeb9f1b6056246a7d563f479f518bb34]]></art>
    <flag>0</flag>
    <preciserating/>
    <rating/>
    <averagerating/>
    <mbid><![CDATA[]]></mbid>
    <summary><![CDATA[]]></summary>
    <time><![CDATA[116]]></time>
    <yearformed>0</yearformed>
    <placeformed><![CDATA[]]></placeformed>
  </artist>
  <artist id="13">
    <name><![CDATA[IOK-1]]></name>
    <genre id="4"><![CDATA[Dark Ambient]]></genre>
    <albums/>
    <albumcount>1</albumcount>
    <songs/>
    <songcount>4</songcount>
    <art><![CDATA[https://music.com.au/image.php?object_id=13&object_type=artist&auth=eeb9f1b6056246a7d563f479f518bb34]]></art>
    <flag>0</flag>
    <preciserating/>
    <rating/>
    <averagerating/>
    <mbid><![CDATA[]]></mbid>
    <summary><![CDATA[IOK-1 was a side project of Tarmskrap, but it became his main project. 
He creates ambient, dark ambient, drone something.

IOK-1 soundcloud 
 
Has released one 3" cdr on Witte Dood Records called "Rost",  appears on Public Spaces Lab's Ceci n’est pas une pipe and Public Spaces Lab's The Future Lab

He released a full length called "Poems" on Deersound. 
It is limited to 10 copies, 4 discs, clocks in at just over five hours. ]]></summary>
    <time><![CDATA[3428]]></time>
    <yearformed>0</yearformed>
    <placeformed><![CDATA[]]></placeformed>
  </artist>
</root>
